{
  "actions": "<a href=\"#\" class=\"prev\"></a><a href=\"#\" class=\"next\"></a>",
  "items": "<div class=\"gallery-item\" data-id=\"801\"><img src=\"gallery08/images/01.jpg\" alt=\"Description,Gallery_08-Image01\" style=\"display: none;\"/></div><div class=\"gallery-item\" data-id=\"802\"><img src=\"gallery08/images/02.jpg\" alt=\"Description,Gallery_08-Image02\" style=\"display: none;\"/></div><div class=\"gallery-item\" data-id=\"803\"><img src=\"gallery08/images/03.jpg\" alt=\"Description,Gallery_08-Image03\" style=\"display: none;\"/></div><div class=\"gallery-item\" data-id=\"804\"><img src=\"gallery08/images/04.jpg\" alt=\"Description,Gallery_08-Image04\" style=\"display: none;\"/></div><div class=\"gallery-item\" data-id=\"805\"><img src=\"gallery08/images/05.jpg\" alt=\"Description,Gallery_08-Image05\" style=\"display: none;\"/></div><div class=\"gallery-item\" data-id=\"806\"><img src=\"gallery08/images/06.jpg\" alt=\"Description,Gallery_08-Image06\" style=\"display: none;\"/></div><div class=\"gallery-item\" data-id=\"607\"><img src=\"gallery08/images/07.jpg\" alt=\"Description,Gallery_08-Image07\" style=\"display: none;\"/></div>",
  "nav": "<ul><li><a href=\"#!gallery08/801/\" data-title=\"<strong>Description,Gallery_08-Image01</strong>,  Glamour\" data-id=\"801\" data-count=\"1\" class=\"current\"><div class=\"gallery-thumb\"><img src=\"gallery08/thumbs/01.jpg\" alt=\"Description,Gallery_08-Image01, Glamour\" /></div></a></li><li><a href=\"#!gallery08/802/\" data-title=\"<strong>Description,Gallery_08-Image02</strong>,  Glamour\" data-id=\"802\" data-count=\"2\" ><div class=\"gallery-thumb\"><img src=\"gallery08/thumbs/02.jpg\" alt=\"Description,Gallery_08-Image02, Glamour\" /></div></a></li><li><a href=\"#!gallery08/803/\" data-title=\"<strong>Description,Gallery_08-Image03</strong>,  Glamour\" data-id=\"803\" data-count=\"3\" ><div class=\"gallery-thumb\"><img src=\"gallery08/thumbs/03.jpg\" alt=\"Description,Gallery_08-Image03, Glamour\" /></div></a></li><li><a href=\"#!gallery08/804/\" data-title=\"<strong>Description,Gallery_08-Image04</strong>,  Glamour\" data-id=\"804\" data-count=\"4\" ><div class=\"gallery-thumb\"><img src=\"gallery08/thumbs/04.jpg\" alt=\"Description,Gallery_08-Image04, Glamour\" /></div></a></li><li><a href=\"#!gallery08/805/\" data-title=\"<strong>Description,Gallery_08-Image05</strong>,  Glamour\" data-id=\"805\" data-count=\"5\" ><div class=\"gallery-thumb\"><img src=\"gallery08/thumbs/05.jpg\" alt=\"Description,Gallery_08-Image05, Glamour\" /></div></a></li><li><a href=\"#!gallery08/806/\" data-title=\"<strong>Description,Gallery_08-Image06</strong>,  Glamour\" data-id=\"806\" data-count=\"6\" ><div class=\"gallery-thumb\"><img src=\"gallery08/thumbs/06.jpg\" alt=\"Description,Gallery_08-Image06, Glamour\" /></div></a></li><li><a href=\"#!gallery08/607/\" data-title=\"<strong>Description,Gallery_08-Image07</strong>,  Glamour\" data-id=\"607\" data-count=\"7\" ><div class=\"gallery-thumb\"><img src=\"gallery08/thumbs/07.jpg\" alt=\"Description,Gallery_08-Image07, Glamour\" /></div></a></li>",
  "title_raw": "Glamour, Gallery 08",
  "title": "<strong>Glamour</strong>,  Gallery 08",
  "content": "",
  "social_facebook": "https://www.facebook.com/sharer/sharer.php?u=http://www.design17.flash-gallery.net",
  "social_twitter": "https://twitter.com/home?status=Gallery 08, Glamour - http%3A%2F%2Fdesign17.flash-gallery.net"
}